azion/__consts__.py
azion/__init__.py
azion/api.py
azion/cli.py
azion/exceptions.py
azion/models.py
azion_api_client-0.0.1a1.dist-info/LICENSE
azion_api_client-0.0.1a1.dist-info/METADATA
azion_api_client-0.0.1a1.dist-info/WHEEL
azion_api_client-0.0.1a1.dist-info/entry_points.txt
azion_api_client-0.0.1a1.dist-info/top_level.txt
azion_api_client-0.0.1a1.dist-info/RECORD
